{
  "geonames:region:2953481": { "code": "DE-BW", "children": {} },
  "geonames:region:2951839": { "code": "DE-BY", "children": {} },
  "geonames:region:2950157": { "code": "DE-BE", "children": {} },
  "geonames:region:2945356": { "code": "DE-BB", "children": {} },
  "geonames:region:2944387": { "code": "DE-HB", "children": {} },
  "geonames:region:2911297": { "code": "DE-HH", "children": {} },
  "geonames:region:2905330": { "code": "DE-HE", "children": {} },
  "geonames:region:2872567": { "code": "DE-MV", "children": {} },
  "geonames:region:2862926": { "code": "DE-NI", "children": {} },
  "geonames:region:2861876": { "code": "DE-NW", "children": {} },
  "geonames:region:2847618": { "code": "DE-RP", "children": {} },
  "geonames:region:2842635": { "code": "DE-SL", "children": {} },
  "geonames:region:2842566": { "code": "DE-SN", "children": {} },
  "geonames:region:2842565": { "code": "DE-ST", "children": {} },
  "geonames:region:2838632": { "code": "DE-SH", "children": {} },
  "geonames:region:2822542": { "code": "DE-TH", "children": {} }
}
